LICENSE
MANIFEST.in
README
chiki_stat.py
setup.py
chiki_stat.egg-info/PKG-INFO
chiki_stat.egg-info/SOURCES.txt
chiki_stat.egg-info/dependency_links.txt
chiki_stat.egg-info/not-zip-safe
chiki_stat.egg-info/requires.txt
chiki_stat.egg-info/top_level.txt