Metadata-Version: 1.0
Name: chiki-stat
Version: 0.0.1
Summary: chiki libs.
Home-page: https://github.com/endsh/chiki-stat
Author: Linshao
Author-email: 438985635@qq.com
License: UNKNOWN
Platform: any
